{
  "_schema": "lingoverse_unit_v1",
  "_extracted": "2026-03-07",
  "unit": {
    "n": 2,
    "lang": "de",
    "title": "Wer bin ich?",
    "sub": "Talk about yourself — where you're from, where you live, and what languages you speak.",
    "level": "A1.1"
  },
  "lessons": [
    {
      "id": "de_u2l1",
      "title": "Woher kommst du? 🌍",
      "steps": [
        {
          "type": "intro",
          "title": "Where Are You From? 🌍",
          "desc": "Germans love to know where you're from — it tells them which dialect to expect! Learn to talk about your origin and nationality.",
          "goals": [
            "Say where you come from",
            "Ask others where they're from",
            "Key countries in German"
          ]
        },
        {
          "type": "teach",
          "nl": "Ich komme aus...",
          "en": "I come from...",
          "img": "🌍✈️",
          "phonetic": "ish KOM-uh ows",
          "example": "Ich komme aus Deutschland.",
          "exampleEn": "I come from Germany.",
          "note": "'Aus' = from/out of. This is THE standard way to state your origin. 'Kommen' follows regular conjugation: ich komme, du kommst, er/sie kommt.",
          "kind": "grammar"
        },
        {
          "type": "teach",
          "nl": "Woher kommst du?",
          "en": "Where do you come from? (informal)",
          "img": "❓🗺️",
          "phonetic": "vo-HAIR komst doo",
          "example": "Hi! Woher kommst du?",
          "exampleEn": "Hi! Where do you come from?",
          "note": "'Woher' = from where. In formal: 'Woher kommen Sie?' Notice the verb is in position 2 — always!",
          "kind": "phrase"
        },
        {
          "type": "teach",
          "nl": "das Land",
          "en": "the country",
          "img": "🗺️🏔️",
          "phonetic": "das lahnt",
          "example": "Deutschland ist ein großes Land.",
          "exampleEn": "Germany is a big country.",
          "note": "A neuter noun (das). Plural: die Länder. Same root as Dutch 'het land' and English 'land'!",
          "kind": "phrase"
        },
        {
          "type": "tip",
          "title": "🌐 Countries in German",
          "text": "Most country names are easy to recognize:\n\n🇩🇪 Deutschland — Germany\n🇦🇹 Österreich — Austria\n🇨🇭 die Schweiz — Switzerland\n🇫🇷 Frankreich — France\n🇬🇧 England — England\n🇺🇸 Amerika / die USA — America\n🇪🇸 Spanien — Spain\n🇮🇹 Italien — Italy\n🇹🇷 die Türkei — Turkey\n🇳🇱 die Niederlande — The Netherlands\n\n⚠️ Some countries need an article:\ndie Schweiz, die Türkei, die USA, die Niederlande\n'Ich komme aus DER Schweiz.' (dative!)"
        },
        {
          "type": "mc",
          "q": "How do you say 'I come from France'?",
          "opts": [
            "Ich komme aus Frankreich",
            "Ich bin Frankreich",
            "Ich gehe nach Frankreich",
            "Ich wohne Frankreich"
          ],
          "ans": "Ich komme aus Frankreich",
          "hint": "Aus = from"
        },
        {
          "type": "teach",
          "nl": "Ich bin...",
          "en": "I am...",
          "img": "🏷️👤",
          "phonetic": "ish bin",
          "example": "Ich bin Deutscher.",
          "exampleEn": "I am German. (male)",
          "note": "Nationalities in German are NOUNS (not adjectives like Dutch!). Male: Deutscher, Female: Deutsche. 'Ich bin Deutscher' vs 'Ich bin Deutsche'.",
          "kind": "phrase"
        },
        {
          "type": "tip",
          "title": "🏳️ Nationalities in German",
          "text": "German nationalities are nouns with GENDER forms:\n\n🇩🇪 Deutscher / Deutsche — German (m/f)\n🇫🇷 Franzose / Französin — French (m/f)\n🇬🇧 Engländer / Engländerin — English (m/f)\n🇪🇸 Spanier / Spanierin — Spanish (m/f)\n🇹🇷 Türke / Türkin — Turkish (m/f)\n🇺🇸 Amerikaner / Amerikanerin — American (m/f)\n\nExamples:\n• Ich bin Deutscher. — I am German. (male)\n• Sie ist Französin. — She is French.\n• Er ist Engländer. — He is English.\n\nFor LANGUAGES, use the adjective form:\n• Ich spreche Deutsch. — I speak German.\n• Er spricht Französisch. — He speaks French.",
          "deepDive": {
            "title": "Nationality ≠ Language in German",
            "text": "Unlike Dutch (where 'Duits' = both German nationality AND language), German separates them:\n\nNATIONALITY (noun): Ich bin Deutscher.\nLANGUAGE (adjective): Ich spreche Deutsch.\n\nThe language is usually the adjective form:\nDeutsch, Französisch, Englisch, Spanisch, Türkisch\n\nBut the nationality is a noun with gender:\nDeutscher/Deutsche, Franzose/Französin, etc.\n\nThis is more complex than Dutch but gives you more precision!"
          }
        },
        {
          "type": "tr",
          "mk": "u2_come_from_france",
          "dir": "produce"
        },
        {
          "type": "mc",
          "q": "A woman says 'Ich bin Deutsche.' This means:",
          "opts": [
            "I am in Germany",
            "I am German",
            "I speak German",
            "I like Germany"
          ],
          "ans": "I am German",
          "hint": "Ich bin = I am, Deutsche = German (female)"
        },
        {
          "type": "fb",
          "s": "_____ kommst du?",
          "a": "Woher",
          "opts": [
            "Woher",
            "Wo",
            "Wohin",
            "Wann"
          ],
          "hint": "FROM where = Wo + her"
        },
        {
          "type": "match",
          "mks": [
            "country_nl",
            "country_de",
            "country_fr",
            "country_gb"
          ]
        }
      ]
    },
    {
      "id": "de_u2l2",
      "title": "Ich wohne in... 🏡",
      "steps": [
        {
          "type": "intro",
          "title": "I Live In... 🏡",
          "desc": "Tell people where you live! Germans will want to know your city — and whether it's in the north or south.",
          "goals": [
            "Say where you live",
            "Ask where someone lives",
            "City vocabulary"
          ]
        },
        {
          "type": "teach",
          "nl": "wohnen",
          "en": "to live (reside)",
          "img": "🏡🔑",
          "phonetic": "VOH-nen",
          "example": "Ich wohne in Berlin.",
          "exampleEn": "I live in Berlin.",
          "note": "'Wohnen' = to reside. Almost identical to Dutch 'wonen'! Conjugation: ich wohne, du wohnst, er/sie wohnt, wir wohnen.",
          "conjugation": {
            "ich": "wohne",
            "du": "wohnst",
            "er/sie": "wohnt",
            "wir": "wohnen",
            "ihr": "wohnt",
            "sie/Sie": "wohnen"
          },
          "kind": "grammar"
        },
        {
          "type": "teach",
          "nl": "die Stadt",
          "en": "the city",
          "img": "🏙️🌃",
          "phonetic": "dee shtat",
          "example": "Berlin ist eine große Stadt.",
          "exampleEn": "Berlin is a big city.",
          "note": "Feminine (die). Plural: die Städte. The umlaut in the plural is typical of German!",
          "kind": "phrase"
        },
        {
          "type": "teach",
          "nl": "das Dorf",
          "en": "the village",
          "img": "🏘️🌳",
          "phonetic": "das dorf",
          "example": "Ich wohne in einem kleinen Dorf.",
          "exampleEn": "I live in a small village.",
          "note": "Neuter (das). Plural: die Dörfer. Germany has thousands of beautiful Dörfer, especially in Bavaria and the Black Forest.",
          "kind": "phrase"
        },
        {
          "type": "teach",
          "nl": "die Straße",
          "en": "the street",
          "img": "🛣️🏠",
          "phonetic": "dee SHTRAH-suh",
          "example": "In welcher Straße wohnst du?",
          "exampleEn": "In which street do you live?",
          "note": "Feminine (die). The 'ß' (Eszett) is unique to German — you can also write 'Strasse'. Street names often end in '-straße', '-weg' (way), or '-allee'.",
          "kind": "phrase"
        },
        {
          "type": "tip",
          "title": "💬 Where do you live?",
          "text": "German small talk about where you live:\n\n❓ Wo wohnst du? — Where do you live?\n💬 Ich wohne in [city]. — I live in [city].\n💬 Ich wohne in der Nähe von... — I live near...\n\nGermans often follow up with:\n❓ Gefällt es dir dort? — Do you like it there?\n❓ Und was machst du beruflich? — And what do you do for work?\n\n🏙️ Big German cities:\nBerlin (capital, ~3.7M)\nMünchen / Munich (Bavaria, ~1.5M)\nHamburg (port city, ~1.9M)\nKöln / Cologne (Rhine, ~1.1M)\nFrankfurt (finance, ~750K)"
        },
        {
          "type": "mc",
          "q": "How do you say 'I live in Munich'?",
          "opts": [
            "Ich bin in München",
            "Ich wohne in München",
            "Ich komme aus München",
            "Ich gehe nach München"
          ],
          "ans": "Ich wohne in München",
          "hint": "Wohnen = to live/reside"
        },
        {
          "type": "tr",
          "mk": "u2_where_live",
          "dir": "comprehend"
        },
        {
          "type": "fb",
          "s": "Ich _____ in einem kleinen Dorf.",
          "a": "wohne",
          "opts": [
            "wohne",
            "bin",
            "komme",
            "gehe"
          ],
          "hint": "Which verb means 'to reside'?"
        },
        {
          "type": "match",
          "mks": [
            "noun_city",
            "noun_village",
            "noun_street",
            "verb_live"
          ]
        },
        {
          "type": "gramref",
          "title": "German Verb Conjugation Basics",
          "level": "A1",
          "text": "German regular verbs follow a predictable pattern:\n\n1. Take the infinitive: wohnen (to live)\n2. Remove -en to get the stem: wohn\n3. Add endings:\n\nich → stem + e (ich wohne)\ndu → stem + st (du wohnst)\ner/sie → stem + t (er wohnt)\nwir → stem + en (wir wohnen)\nihr → stem + t (ihr wohnt)\nsie/Sie → stem + en (sie wohnen)\n\nAlmost identical to Dutch! The 'du' and 'ihr' forms are the main difference."
        },
        {
          "type": "conj",
          "verb": "wohnen",
          "en": "to live/reside",
          "forms": {
            "ich": "wohne",
            "du": "wohnst",
            "er": "wohnt",
            "wir": "wohnen",
            "ihr": "wohnt",
            "sie": "wohnen"
          },
          "test": [
            "ich",
            "du",
            "wir"
          ]
        },
        {
          "type": "tr",
          "mk": "u2_city_beautiful",
          "dir": "produce"
        }
      ]
    },
    {
      "id": "de_u2l3",
      "title": "Sprachen 🗣️",
      "steps": [
        {
          "type": "intro",
          "title": "Languages I Speak 🗣️",
          "desc": "Germany dubs EVERYTHING — so they've had less English exposure than the Dutch! Learn to talk about languages.",
          "goals": [
            "Say what languages you speak",
            "Ask if someone speaks German",
            "'Ein bisschen' (a little)"
          ]
        },
        {
          "type": "teach",
          "nl": "sprechen",
          "en": "to speak",
          "img": "🗣️💬",
          "phonetic": "SHPREH-khen",
          "example": "Sprichst du Deutsch?",
          "exampleEn": "Do you speak German?",
          "note": "An irregular (strong) verb! ich spreche, du SPRICHST, er SPRICHT. The 'e' changes to 'i' in du/er forms. This is called a 'vowel change' verb.",
          "conjugation": {
            "ich": "spreche",
            "du": "sprichst",
            "er/sie": "spricht",
            "wir": "sprechen",
            "ihr": "sprecht",
            "sie/Sie": "sprechen"
          },
          "kind": "grammar"
        },
        {
          "type": "teach",
          "nl": "ein bisschen",
          "en": "a little",
          "img": "🤏😅",
          "phonetic": "ayn BIS-khen",
          "example": "Ich spreche ein bisschen Deutsch.",
          "exampleEn": "I speak a little German.",
          "note": "Super useful! 'Bisschen' comes from 'Biss' (bite) — literally 'a little bite'. Similar to Dutch 'een beetje'.",
          "kind": "phrase"
        },
        {
          "type": "teach",
          "nl": "die Sprache",
          "en": "the language",
          "img": "🌐📖",
          "phonetic": "dee SHPRAH-khuh",
          "example": "Deutsch ist eine schöne Sprache.",
          "exampleEn": "German is a beautiful language.",
          "note": "Feminine (die). Plural: die Sprachen. 'Muttersprache' = mother tongue. Related to 'sprechen' (to speak).",
          "kind": "phrase"
        },
        {
          "type": "tip",
          "title": "🇩🇪 Germans and languages",
          "text": "Unlike the Dutch, most Germans grew up with DUBBED TV and movies. This means English skills vary a lot!\n\nUseful phrases:\n• Ich spreche Deutsch. — I speak German.\n• Ich spreche ein bisschen Deutsch. — I speak a little German.\n• Sprichst du Englisch? — Do you speak English?\n• Ich lerne Deutsch. — I am learning German.\n• Ich verstehe dich nicht. — I don't understand you.\n\nPro tip: In big cities (Berlin, Munich, Hamburg) many people speak English. In smaller towns and in the East, less so. Always try German first — it's greatly appreciated!",
          "deepDive": {
            "title": "Why German TV is dubbed",
            "text": "Germany, Austria, and Switzerland dub ALL foreign content — movies, TV series, everything.\n\nThis is a huge industry: Germany has world-class dubbing studios, and famous actors have a dedicated 'Synchronsprecher' (voice actor) who dubs all their roles.\n\nTom Hanks always sounds the same in German — because the same voice actor has dubbed him for 30+ years!\n\nThe downside: less casual English exposure compared to the Dutch or Scandinavians. The upside: German dubbing quality is considered the best in the world."
          }
        },
        {
          "type": "mc",
          "q": "How do you say 'I speak a little German'?",
          "opts": [
            "Ich spreche Deutsch",
            "Ich spreche ein bisschen Deutsch",
            "Ich lerne Deutsch",
            "Ich verstehe Deutsch"
          ],
          "ans": "Ich spreche ein bisschen Deutsch",
          "hint": "Ein bisschen = a little"
        },
        {
          "type": "tr",
          "mk": "u2_speak_english",
          "dir": "produce"
        },
        {
          "type": "fb",
          "s": "Ich spreche ein _____ Deutsch.",
          "a": "bisschen",
          "opts": [
            "bisschen",
            "großes",
            "viel",
            "gutes"
          ],
          "hint": "A little = ein _____"
        },
        {
          "type": "tr",
          "mk": "u2_lang_beautiful",
          "dir": "comprehend"
        },
        {
          "type": "mc",
          "q": "What does 'Ich lerne Deutsch' mean?",
          "opts": [
            "I speak German",
            "I am German",
            "I am learning German",
            "I understand German"
          ],
          "ans": "I am learning German",
          "hint": "Lernen = to learn"
        },
        {
          "type": "gramref",
          "title": "Vowel Change Verbs",
          "level": "A1",
          "text": "Some German verbs change their stem vowel in du/er/sie forms:\n\nSprechen (to speak): e → i\nich spreche, du sprichst, er spricht\n\nOther common ones:\n• sehen (to see): du siehst, er sieht\n• lesen (to read): du liest, er liest\n• geben (to give): du gibst, er gibt\n• nehmen (to take): du nimmst, er nimmt\n\nOnly the du and er/sie/es forms change. Wir/ihr/sie stay regular."
        },
        {
          "type": "conj",
          "verb": "sprechen",
          "en": "to speak",
          "forms": {
            "ich": "spreche",
            "du": "sprichst",
            "er": "spricht",
            "wir": "sprechen",
            "ihr": "sprecht",
            "sie": "sprechen"
          },
          "test": [
            "ich",
            "du",
            "er"
          ]
        }
      ]
    },
    {
      "id": "de_u2l4",
      "title": "Alles über mich 💫",
      "steps": [
        {
          "type": "intro",
          "title": "All About Me 💫",
          "desc": "Combine everything! Introduce yourself fully in German — name, origin, city, and languages.",
          "goals": [
            "Full self-introduction",
            "Practice all Unit 2 vocabulary",
            "Mini-conversation patterns"
          ]
        },
        {
          "type": "tip",
          "title": "🎯 Your German self-intro",
          "text": "Here's a full self-introduction pattern:\n\nHallo! Ich heiße [name]. — Hello! My name is [name].\nIch komme aus [country]. — I come from [country].\nIch wohne in [city]. — I live in [city].\nIch spreche [language] und ein bisschen Deutsch. — I speak [language] and a little German.\nFreut mich! — Nice to meet you!\n\nExample:\nHallo! Ich heiße Maria. — Hello! My name is Maria.\nIch komme aus Spanien. — I come from Spain.\nIch wohne in Berlin. — I live in Berlin.\nIch spreche Spanisch und ein bisschen Deutsch. — I speak Spanish and a little German.\nFreut mich! — Nice to meet you!"
        },
        {
          "type": "tr",
          "mk": "u2_name_origin",
          "dir": "comprehend"
        },
        {
          "type": "fb",
          "s": "Ich _____ aus Frankreich.",
          "a": "komme",
          "opts": [
            "komme",
            "wohne",
            "spreche",
            "heiße"
          ],
          "hint": "I come FROM France"
        },
        {
          "type": "mc",
          "q": "Someone says 'Wo wohnst du?' — you reply:",
          "opts": [
            "Ich heiße Anna",
            "Ich komme aus Deutschland",
            "Ich wohne in München",
            "Ich spreche Deutsch"
          ],
          "ans": "Ich wohne in München",
          "hint": "They're asking WHERE you live"
        },
        {
          "type": "tr",
          "mk": "u2_live_speak_little",
          "dir": "produce"
        },
        {
          "type": "match",
          "mks": [
            "phrase_my_name_is",
            "phrase_i_come_from",
            "phrase_i_live_in",
            "phrase_i_speak"
          ]
        },
        {
          "type": "mc",
          "q": "How do you say 'Nice to meet you' in German?",
          "opts": [
            "Bitte schön",
            "Freut mich",
            "Guten Tag",
            "Danke"
          ],
          "ans": "Freut mich",
          "hint": "You learned this in Unit 1!"
        }
      ]
    }
  ]
}
